Verilog/FullAdder.sv
module fadder(y,c1,a,b,c);
input a,b,c;
output y,c1;
wire z,z1,z2;
xor(z,a,b);
xor(y,z,c);
and(z1,z,c);
and(z2,a,b);
or(c1,z1,z2);
endmodule

Verilog/FullAdder1.sv
module test_fadder;
reg a,b,c;
wire y,c1;
fadder f(y,c1,a,b,c);
initial
begin
$dumpfile("adder.vcd");
$dumpvars;
a=0;b=0;c=0;
#10 a=0;b=0;c=1;
#10 a=0;b=1;c=0;
#10 a=0;b=1;c=1;
#10 a=1;b=0;c=0;
#10 a=1;b=0;c=1;
#10 a=1;b=1;c=0;
#10 a=1;b=1;c=1;
#10 $finish;
end
endmodule

Verilog/adder.vcd
$date
	Mon Aug 29 16:51:01 2022
$end
$version
	Icarus Verilog
$end
$timescale
	1s
$end
$scope module test_fadder $end
$var wire 1 ! y $end
$var wire 1 " c1 $end
$var reg 1 # a $end
$var reg 1 $ b $end
$var reg 1 % c $end
$scope module f $end
$var wire 1 # a $end
$var wire 1 $ b $end
$var wire 1 % c $end
$var wire 1 " c1 $end
$var wire 1 ! y $end
$var wire 1 & z $end
$var wire 1 ' z1 $end
$var wire 1 ( z2 $end
$upscope $end
$upscope $end
$enddefinitions $end
$comment Show the parameter values. $end
$dumpall
$end
#0
$dumpvars
0(
0'
0&
0%
0$
0#
0"
0!
$end
#10
1!
1%
#20
1&
0%
1$
#30
1"
0!
1'
1%
#40
0"
1!
0'
0%
0$
1#
#50
1"
0!
1'
1%
#60
0'
0&
1(
0%
1$
#70
1!
1%
