Verilog/JKFFDesign.sv
module jkff(input reset, input clk, input j, input k, output reg q, output qnot);
assign qnot=~q;
always @(negedge clk)
begin if (reset) q<=1'b0;
else case ({j, k}) 2'b00: q<=q;
2'b01: q<=1'b0;
2'b10: q<=1'b1;
2'b11: q<=~q;
endcase
end
endmodule

Verilog/JKFFTestbench.sv
module test;
reg clk=0;
reg j=0;
reg k=0;
reg reset;
wire q, qnot;
jkff dut(reset , clk,j,k,q,qnot);
initial begin $dumpfile("dump.vcd");
$dumpvars;
reset=1'b1;
#10 reset=1'b0;
j=1'b0; k=1'b1;
#20 reset=1'b0;
j=1'b0; k=1'b0;
 #20 reset=1'b0;
j=1'b1; k=1'b0;
#20 reset=1'b0;
j=1'b1; k=1'b1;
#40 $finish;
end always #5 clk=~clk;
endmodule

Verilog/dump.vcd
$date
	Tue Sep 13 23:21:24 2022
$end
$version
	Icarus Verilog
$end
$timescale
	1s
$end
$scope module test $end
$var wire 1 ! qnot $end
$var wire 1 " q $end
$var reg 1 # clk $end
$var reg 1 $ j $end
$var reg 1 % k $end
$var reg 1 & reset $end
$scope module dut $end
$var wire 1 # clk $end
$var wire 1 $ j $end
$var wire 1 % k $end
$var wire 1 ! qnot $end
$var wire 1 & reset $end
$var reg 1 " q $end
$upscope $end
$upscope $end
$enddefinitions $end
$comment Show the parameter values. $end
$dumpall
$end
#0
$dumpvars
1&
0%
0$
0#
0"
1!
$end
#5
1#
#10
0#
1%
0&
#15
1#
#20
0#
#25
1#
#30
0#
0%
#35
1#
#40
0#
#45
1#
#50
0!
1"
0#
1$
#55
1#
#60
0#
#65
1#
#70
1!
0"
0#
1%
#75
1#
#80
0!
1"
0#
#85
1#
#90
1!
0"
0#
#95
1#
#100
0!
1"
0#
#105
1#
#110
1!
0"
0#
